mnswpr.py
mnswpr-1.0.0.dist-info/entry_points.txt
mnswpr-1.0.0.dist-info/WHEEL
mnswpr-1.0.0.dist-info/METADATA
mnswpr-1.0.0.dist-info/RECORD
