Metadata-Version: 2.1
Name: mnswpr
Version: 1.0.0
Summary: minesweeper
Author: worldmaker
Author-email: worldmaker18349276@gmail.com
Requires-Python: >=3.8,<4.0
Classifier: Programming Language :: Python :: 3
Classifier: Programming Language :: Python :: 3.10
Classifier: Programming Language :: Python :: 3.8
Classifier: Programming Language :: Python :: 3.9
Requires-Dist: numpy (>=1.18.5,<2.0.0)
